cbr_custom_open_sec_summit/__init__.py
cbr_custom_open_sec_summit/fast_api/Open_Sec_Summit__Fast_API.py
cbr_custom_open_sec_summit/fast_api/__init__.py
cbr_custom_open_sec_summit/fast_api/routes/Routes__Info.py
cbr_custom_open_sec_summit/fast_api/routes/__init__.py
cbr_custom_open_sec_summit/lambdas/__init__.py
cbr_custom_open_sec_summit/lambdas/handler.py
cbr_custom_open_sec_summit/markitdown/Markitdown_Service.py
cbr_custom_open_sec_summit/markitdown/routes/Routes__Markitdown.py
cbr_custom_open_sec_summit/markitdown/sample_files/sample.pdf
cbr_custom_open_sec_summit/markitdown/sample_files/test.jpg
cbr_custom_open_sec_summit/markitdown/sample_files/test.xlsx
cbr_custom_open_sec_summit/testing/__init__.py
cbr_custom_open_sec_summit/testing/open_sec_summit__objs_for_tests.py
cbr_custom_open_sec_summit/utils/Version.py
cbr_custom_open_sec_summit/utils/__init__.py
cbr_custom_open_sec_summit/version
cbr_custom_open_sec_summit-0.7.0.dist-info/LICENSE
cbr_custom_open_sec_summit-0.7.0.dist-info/METADATA
cbr_custom_open_sec_summit-0.7.0.dist-info/WHEEL
cbr_custom_open_sec_summit-0.7.0.dist-info/RECORD
